{"paths":{},"types":[],"uuids":["01mFcjc79LFIJT4A+4+F+I","0aVA1hkGhNu7ulo1E2mXmJ","0ekZvadOtE87cistI3EGHA","18c/BweDxKoJI8QoqXszmI","29FYIk+N1GYaeWH/q1NxQO","43V/DnPnpCKpJHLl+YlP7m","4cJZV8NGlBu5ko5T2KVCV6","4f32m8MCBB7Y2y1hFHYFWr","55HJexCJdCt656qOLKTsOc","56FiHk+lJLd4uqMophF8vY","60TaQaxstOk45JQle6hgVy","61cyPdEfRN047sDK9rO0W5","63ENoHU9lLppQ9RGVBI73A","63trq203xI/4k0YTDFNc9M","64aJNEXYZCCqRyyVDFcUbt","67gfYKrZ1FeLWS/PAWN9+O","6bhVuScQFJJqJXqaht3j34","71VhFCTINJM6/Ky3oX9nBT","73DwpIZixHfo43q+HB0hTJ","78+1Wai0FBar6ll7KYcCO1","82NNl7YuVMJqEGb6vUvwZD","89/U6Ftq9MRr0luG/fe1Bm","8dQ1XinRhA9aNtaRGqoW9j","8f8BVVLr5Lkr2T5oWPw+qb","9452UwUL1I6Z5Ug7R6wIYF","9dTNygjqlL2KILbIXx5g8g","a2MjXRFdtLlYQ5ouAFv/+R","a2lcfffdJP4bhLiCVve17R","a3tf8gcpFCTKtxieGYqlaN","aauM7prgRHj742JcfPbmSf","abBdDQbPxKbYuL9WPu7isp","b0nLoye6JFXZaqsgsFHj4M","b2aHrECZ5APKGS/0d2hvT1","b3nmOSA2JJ0Lr80bsovC8O","b4P/PCArtIdIH38t6mlw8Y","b6b/t4ci1ITZO05HwBlfMW","b78cPh3bFEpamrekFX8ck2","baxTuBSHpNn6NSyXH9MqiJ","c3AYlqgh5LV4DKS8lGTBbU","c7zLmpcZNKSZCaRt5WxpUg","cbbQe4VZBCxqPOkUQOad5d","d0qC05vt5GxLaYyB/w3t//","d608qFRoFHwbXd0Dap056i","d7WMjpDMZEd4+4ixJQy9rm","e3bVtWkFlIZrXKu307Iq4O","e5x6TCKCNASZYfqKI1ox0/","e8Ueib+qJEhL6mXAHdnwbi","e97GVMl6JHh5Ml5qEDdSGa","f0BIwQ8D5Ml7nTNQbh1YlS","f6euGkJZJBo7Fh1kb0H30I","f9YJjOMXZFobZ/pOY+S40X","fbcMZxzehNfK/cW5iynZAp","fde4EqNAxIILNgbZ4ttWBQ","fdy3PRvs5AKLWrqzbq5tnU","02delMVqdBD70a/HSD99FK","0dMc1+6f1KWJZdAytYfIhK","13yrVcQktGDZ8q8mLvITLI","16dwAe62BM0bDBsabOybJW","1aKTAIgSZJ446xgCOxMFZy","1bE1XNEo1Co45Zr9dGzJgY","1cQHt2P/BHm6Lp5jP2SScI","26nhOZt0tGP4tHQYcwp/G0","295fmFab5LvbgvUgyP+qz6","2anX5qb3dOn5ZzflcnvsgA","2dxYuRxylLna+Wrar5R/fU","3102km1d1AToNQ/KvQHYeu","32aei3qUpLypyM0hyCoGHn","3cfiFAcqFNS4lTebMfqt4j","40dUesqJBPWr+osV0+ck+8","41oFkVRExM26KOr33QpTlV","47LfXTNedBhJ5sf0G+5l7j","49FOJ1RP5Dta9QGweOIiK/","4aBU/2jUJBMppeTgJfulVP","5bUF7joW5NdZ+IVeb+dHEi","5byRxDqNlKTLcz7o+ZnH4y","5cO7kybDxGj4ipyMYdRYZB","5ef3A6ETJHT50A+2nb5lGK","5f0D+7s/9LP4TblyzeFR+A","5f5dyqtRNNxaFmVzYns6FZ","691JZZ9Y9NnKeu//120vf4","6bYWAvadFNIJ+Z7T7xvBGe","6cXvb5CpNPB7K3GROaGQXB","6do/m6hKFEjqnEXKj7MFMU","80Sy2jiE9HQ7A01TGa8LCt","81egKGertGqKEofd1PP9Ik","83/HMiA7BPir3VrZ38rWM4","84ny5hw19N7ZVmQ7Wenu8p","85Td6OvvRD/rD/bXrH+M2n","866tP7+99Lk7rGuJeUtqAL","88SGa+4qdJ9b1gDhnOxvJF","98A69zCy9IR7I9bir8FvPF","9aHf3RUy9AnbdS/06ONt6k","9bhtmdB8dLw5WhOnXG38i7","9cLfvh1YtK7ocy9mVP9FQM","9eIahddh5PR4RkIQPwo16p","a4nyMhA2NMz5J+z3Rg0BTU","a456OpC+tHCrbF7xL2kRHE","ad6Tt+Af9DrL0lKpfWRb0s","ae4MC9fOVFnpY8zqTTonLF","afMHjaSIxENpYcFgSr1qRm","b0Bq1jryxCzo2UAHDMUg5Y","b1HF0PtLVGMK2qN59RKfgW","b6e/G/kZZPqoX36Vl7xUQY","b7Pk4hFbpBBprlqlQpulNg","c2I0+cV8BP5bA1IPr4vram","d1XIlZzYRPDZnksjSDcWlU","d5Up5oWRpBU4Erpz/BWHid","d9vO8jriVA/4EbSp72eKZY","dbLWY9LTRA25BrJWm8s7u0","dbilU2O81GwpVjbgAuRFVS","dcv7JzaOJC47ZKcNcV7Pgy","ddjzbBglJOS5pB9Yv1d+Li","e6SuxdjXZME4Vxe2cuMs7S","e8PRwIIkhNr4Ugv0wcHWne","eca5qiOxVEqYTT3yY/Rumd","ecpdLyjvZBwrvm+cedCcQy","edBgr1dXxDm6aN17zsy70l","edbDOAwhFNPrZ82SXFeJGg","eerpcSp8FMH53du9ZBqHBt","fb7oCcS6JDs4WqK2txUkw1","feJX14KJ9Ee46TOt5GpF8F","ffGGSlPqlNEa8KbrdB38cS"],"scenes":{"db://assets/scenes/ingame.fire":37,"db://assets/scenes/landing.fire":1},"redirect":[54,0,115,0],"deps":["internal"],"packs":{"0c884287a":[55,56,57,58,59,60,61,4,62,63,64,65,66,67,68,69,5,70,71,72,6,9,73,74,76,77,10,12,80,16,81,82,83,84,85,86,87,88,89,24,90,91,92,93,25,94,26,95,96,97,99,100,32,35,103,37,104,105,107,108,109,111,112,113,47,114,116,117,118,48,50,51,119,52,53,120],"0ca6651e4":[0,2,7,8,11,13,14,15,17,18,19,20,21,22,23,27,28,29,30,31,33,34,36,38,39,40,41,42,43,44,45,46,49],"0ccfc7799":[1,4,9,75,78,10,79,26,98,101,35,102,106,110,47,48,50,53,121]},"name":"main","importBase":"import","nativeBase":"native","debug":false,"isZip":false,"encrypted":false,"versions":{"import":["0c884287a","c2ef7","0ca6651e4","2334f","0ccfc7799","8c0aa",3,"31eb2"],"native":[0,"b15f2",2,"a50a2",3,"113af",5,"e54de",6,"ec0c7",7,"a757d",8,"90a1d",11,"6d707",12,"53c30",13,"8b292",14,"1011c",15,"8818c",16,"b685c",17,"c06a9",18,"7264a",19,"72cf7",20,"07f9f",21,"50c96",22,"8a0ee",23,"20181",24,"eced7",25,"209aa",27,"ef333",28,"ce47d",29,"baf43",30,"f5e98",31,"a7bd6",32,"2bf0b",33,"ec352",34,"83fcc",36,"bf216",38,"2efe4",39,"ab8e9",40,"29b0c",41,"841f5",42,"d55c2",43,"44ab1",44,"dfc55",45,"07e83",46,"90cf4",49,"96813",51,"22d51",52,"a108b"]}}